Metadata-Version: 2.1
Name: modified-repository-miner
Version: 1.0.8
Summary: A tool to mine software repositories for defect prediction.
Home-page: https://github.com/GerardoBrescia/radon-modified-miner
Author: Gerardo Brescia
Author-email: gerrybrescia99@gmail.com
Maintainer: Gerardo Brescia
License: Apache License
Classifier: Development Status :: 5 - Production/Stable
Classifier: Intended Audience :: Developers
Classifier: Programming Language :: Python :: 3.6
Classifier: Programming Language :: Python :: 3.7
Classifier: Programming Language :: Python :: 3.8
Classifier: Programming Language :: Python :: 3.9
Classifier: License :: OSI Approved :: Apache Software License
Classifier: Topic :: Software Development :: Libraries :: Python Modules
Classifier: Operating System :: POSIX :: Linux
Requires-Python: >=3.6
License-File: LICENSE
Requires-Dist: ansiblemetrics
Requires-Dist: dataclasses (~=0.6)
Requires-Dist: nltk (~=3.5)
Requires-Dist: pandas (~=1.1.4)
Requires-Dist: pydriller (==2.0)
Requires-Dist: pyyaml (~=6.0.1)
Requires-Dist: spacy (~=2.3.4)
Requires-Dist: tosca-metrics (~=0.0.8)
Requires-Dist: terraformmetrics (==1.0.6)
Requires-Dist: python-hcl2 (~=4.3.2)
